lektor_gulp_support.py
lektor_gulp_support-0.1.2.dist-info/DESCRIPTION.rst
lektor_gulp_support-0.1.2.dist-info/METADATA
lektor_gulp_support-0.1.2.dist-info/RECORD
lektor_gulp_support-0.1.2.dist-info/WHEEL
lektor_gulp_support-0.1.2.dist-info/entry_points.txt
lektor_gulp_support-0.1.2.dist-info/metadata.json
lektor_gulp_support-0.1.2.dist-info/top_level.txt
