Metadata-Version: 2.0
Name: lektor-gulp-support
Version: 0.1.2
Summary: Adds support for gulp to Lektor
Home-page: http://github.com/selgem/lektor-gulp-support
Author: Drayuk
Author-email: ekentiako@gmail.com
License: MIT
Platform: UNKNOWN
